JiqiXuexiJinjieBijiDaUDeJishuKetang/README.md
JiqiXuexiJinjieBijiDaUDeJishuKetang/__init__.py
JiqiXuexiJinjieBijiDaUDeJishuKetang/__main__.py
JiqiXuexiJinjieBijiDaUDeJishuKetang/file.epub
JiqiXuexiJinjieBijiDaUDeJishuKetang/index.html
JiqiXuexiJinjieBijiDaUDeJishuKetang/css/__init__.py
JiqiXuexiJinjieBijiDaUDeJishuKetang/css/annotations.css
JiqiXuexiJinjieBijiDaUDeJishuKetang/css/main.css
JiqiXuexiJinjieBijiDaUDeJishuKetang/css/normalize.css
JiqiXuexiJinjieBijiDaUDeJishuKetang/css/popup.css
JiqiXuexiJinjieBijiDaUDeJishuKetang/font/__init__.py
JiqiXuexiJinjieBijiDaUDeJishuKetang/font/fontello.eot
JiqiXuexiJinjieBijiDaUDeJishuKetang/font/fontello.svg
JiqiXuexiJinjieBijiDaUDeJishuKetang/font/fontello.ttf
JiqiXuexiJinjieBijiDaUDeJishuKetang/font/fontello.woff
JiqiXuexiJinjieBijiDaUDeJishuKetang/img/__init__.py
JiqiXuexiJinjieBijiDaUDeJishuKetang/img/annotator-glyph-sprite.png
JiqiXuexiJinjieBijiDaUDeJishuKetang/img/annotator-icon-sprite.png
JiqiXuexiJinjieBijiDaUDeJishuKetang/img/apple-touch-icon.png
JiqiXuexiJinjieBijiDaUDeJishuKetang/img/cancelfullscreen.png
JiqiXuexiJinjieBijiDaUDeJishuKetang/img/close.png
JiqiXuexiJinjieBijiDaUDeJishuKetang/img/fullscreen.png
JiqiXuexiJinjieBijiDaUDeJishuKetang/img/loader.gif
JiqiXuexiJinjieBijiDaUDeJishuKetang/img/menu-icon.png
JiqiXuexiJinjieBijiDaUDeJishuKetang/img/save.png
JiqiXuexiJinjieBijiDaUDeJishuKetang/img/saved.png
JiqiXuexiJinjieBijiDaUDeJishuKetang/img/settings-s.png
JiqiXuexiJinjieBijiDaUDeJishuKetang/img/settings.png
JiqiXuexiJinjieBijiDaUDeJishuKetang/img/star.png
JiqiXuexiJinjieBijiDaUDeJishuKetang/js/__init__.py
JiqiXuexiJinjieBijiDaUDeJishuKetang/js/epub.js
JiqiXuexiJinjieBijiDaUDeJishuKetang/js/epub.min.js
JiqiXuexiJinjieBijiDaUDeJishuKetang/js/epub.min.map
JiqiXuexiJinjieBijiDaUDeJishuKetang/js/hooks.min.js
JiqiXuexiJinjieBijiDaUDeJishuKetang/js/hooks.min.map
JiqiXuexiJinjieBijiDaUDeJishuKetang/js/reader.js
JiqiXuexiJinjieBijiDaUDeJishuKetang/js/reader.js.map
JiqiXuexiJinjieBijiDaUDeJishuKetang/js/reader.min.js
jiqi_xuexi_jinjie_biji_da_u_de_jishu_ketang-2024.3.3.0.dist-info/METADATA
jiqi_xuexi_jinjie_biji_da_u_de_jishu_ketang-2024.3.3.0.dist-info/WHEEL
jiqi_xuexi_jinjie_biji_da_u_de_jishu_ketang-2024.3.3.0.dist-info/entry_points.txt
jiqi_xuexi_jinjie_biji_da_u_de_jishu_ketang-2024.3.3.0.dist-info/top_level.txt
jiqi_xuexi_jinjie_biji_da_u_de_jishu_ketang-2024.3.3.0.dist-info/RECORD
